hackery
