Metadata-Version: 1.0
Name: Hackery
Version: 0.0.7
Summary: hack labeling and tracking library
Home-page: http://github.com/gamechanger/hackery.py
Author: Kiril Savino
Author-email: kiril@gamechanger.io
License: BSD
Keywords: hack
Platform: UNKNOWN
